{
  "annotations": {
    "list": [
      {
        "builtIn": 1,
        "datasource": {
          "type": "grafana",
          "uid": "-- Grafana --"
        },
        "enable": true,
        "hide": true,
        "iconColor": "rgba(0, 211, 255, 1)",
        "name": "Annotations & Alerts",
        "type": "dashboard"
      }
    ]
  },
  "editable": true,
  "fiscalYearStartMonth": 0,
  "graphTooltip": 0,
  "id": 1,
  "links": [],
  "liveNow": false,
  "panels": [
    {
      "datasource": {
        "type": "grafana-postgresql-datasource",
        "uid": "e47d9667-cfa2-47f7-841f-2031975ca3d6"
      },
      "fieldConfig": {
        "defaults": {
          "color": {
            "fixedColor": "purple",
            "mode": "continuous-GrYlRd"
          },
          "mappings": [],
          "max": 150,
          "thresholds": {
            "mode": "absolute",
            "steps": [
              {
                "color": "green",
                "value": null
              },
              {
                "color": "red",
                "value": 50
              }
            ]
          }
        },
        "overrides": []
      },
      "gridPos": {
        "h": 8,
        "w": 4,
        "x": 0,
        "y": 0
      },
      "id": 5,
      "options": {
        "minVizHeight": 200,
        "minVizWidth": 200,
        "orientation": "auto",
        "reduceOptions": {
          "calcs": [
            "last"
          ],
          "fields": "/^latency_ms$/",
          "values": false
        },
        "showThresholdLabels": true,
        "showThresholdMarkers": true,
        "sizing": "auto"
      },
      "pluginVersion": "10.2.3",
      "targets": [
        {
          "datasource": {
            "type": "grafana-postgresql-datasource",
            "uid": "e47d9667-cfa2-47f7-841f-2031975ca3d6"
          },
          "editorMode": "code",
          "format": "table",
          "rawQuery": true,
          "rawSql": "select created_on as time\n, case\n     when latency_ms is null then 1000\n     else latency_ms\nend as latency_ms\nfrom latency_metric;",
          "refId": "A",
          "sql": {
            "columns": [
              {
                "parameters": [],
                "type": "function"
              }
            ],
            "groupBy": [
              {
                "property": {
                  "type": "string"
                },
                "type": "groupBy"
              }
            ],
            "limit": 50
          }
        }
      ],
      "title": "Latency (ms)",
      "type": "gauge"
    },
    {
      "datasource": {
        "type": "grafana-postgresql-datasource",
        "uid": "e47d9667-cfa2-47f7-841f-2031975ca3d6"
      },
      "fieldConfig": {
        "defaults": {
          "color": {
            "fixedColor": "purple",
            "mode": "thresholds"
          },
          "mappings": [],
          "max": 350,
          "thresholds": {
            "mode": "absolute",
            "steps": [
              {
                "color": "red",
                "value": null
              },
              {
                "color": "#EAB839",
                "value": 50
              },
              {
                "color": "green",
                "value": 100
              }
            ]
          }
        },
        "overrides": []
      },
      "gridPos": {
        "h": 8,
        "w": 4,
        "x": 4,
        "y": 0
      },
      "id": 6,
      "options": {
        "minVizHeight": 200,
        "minVizWidth": 200,
        "orientation": "auto",
        "reduceOptions": {
          "calcs": [
            "last"
          ],
          "fields": "",
          "values": false
        },
        "showThresholdLabels": false,
        "showThresholdMarkers": true,
        "sizing": "auto"
      },
      "pluginVersion": "10.2.3",
      "targets": [
        {
          "datasource": {
            "type": "grafana-postgresql-datasource",
            "uid": "e47d9667-cfa2-47f7-841f-2031975ca3d6"
          },
          "editorMode": "code",
          "format": "table",
          "rawQuery": true,
          "rawSql": "select created_on as time\n, case\n     when download_kbs is null then 0\n     else download_kbs / 1024.0\nend as download_mbps\nfrom bandwidth_metric;",
          "refId": "A",
          "sql": {
            "columns": [
              {
                "parameters": [],
                "type": "function"
              }
            ],
            "groupBy": [
              {
                "property": {
                  "type": "string"
                },
                "type": "groupBy"
              }
            ],
            "limit": 50
          }
        }
      ],
      "title": "Download (mbps)",
      "type": "gauge"
    },
    {
      "datasource": {
        "type": "grafana-postgresql-datasource",
        "uid": "e47d9667-cfa2-47f7-841f-2031975ca3d6"
      },
      "fieldConfig": {
        "defaults": {
          "color": {
            "fixedColor": "purple",
            "mode": "thresholds"
          },
          "mappings": [],
          "max": 50,
          "thresholds": {
            "mode": "absolute",
            "steps": [
              {
                "color": "red",
                "value": null
              },
              {
                "color": "#EAB839",
                "value": 10
              },
              {
                "color": "green",
                "value": 20
              }
            ]
          }
        },
        "overrides": []
      },
      "gridPos": {
        "h": 8,
        "w": 4,
        "x": 8,
        "y": 0
      },
      "id": 7,
      "options": {
        "minVizHeight": 200,
        "minVizWidth": 200,
        "orientation": "auto",
        "reduceOptions": {
          "calcs": [
            "last"
          ],
          "fields": "",
          "values": false
        },
        "showThresholdLabels": false,
        "showThresholdMarkers": true,
        "sizing": "auto"
      },
      "pluginVersion": "10.2.3",
      "targets": [
        {
          "datasource": {
            "type": "grafana-postgresql-datasource",
            "uid": "e47d9667-cfa2-47f7-841f-2031975ca3d6"
          },
          "editorMode": "code",
          "format": "table",
          "rawQuery": true,
          "rawSql": "select created_on as time\n, case\n     when upload_kbs is null then 0\n     else upload_kbs / 1024.0\nend as upload_mbps\nfrom bandwidth_metric;",
          "refId": "A",
          "sql": {
            "columns": [
              {
                "parameters": [],
                "type": "function"
              }
            ],
            "groupBy": [
              {
                "property": {
                  "type": "string"
                },
                "type": "groupBy"
              }
            ],
            "limit": 50
          }
        }
      ],
      "title": "Upload (mbps)",
      "type": "gauge"
    },
    {
      "datasource": {
        "type": "grafana-postgresql-datasource",
        "uid": "e47d9667-cfa2-47f7-841f-2031975ca3d6"
      },
      "fieldConfig": {
        "defaults": {
          "color": {
            "fixedColor": "red",
            "mode": "fixed"
          },
          "custom": {
            "axisBorderShow": false,
            "axisCenteredZero": false,
            "axisColorMode": "text",
            "axisLabel": "",
            "axisPlacement": "auto",
            "barAlignment": 0,
            "drawStyle": "points",
            "fillOpacity": 0,
            "gradientMode": "none",
            "hideFrom": {
              "legend": false,
              "tooltip": false,
              "viz": false
            },
            "insertNulls": false,
            "lineInterpolation": "linear",
            "lineWidth": 1,
            "pointSize": 11,
            "scaleDistribution": {
              "type": "linear"
            },
            "showPoints": "auto",
            "spanNulls": false,
            "stacking": {
              "group": "A",
              "mode": "none"
            },
            "thresholdsStyle": {
              "mode": "off"
            }
          },
          "mappings": [],
          "thresholds": {
            "mode": "absolute",
            "steps": [
              {
                "color": "green",
                "value": null
              },
              {
                "color": "red",
                "value": 50
              }
            ]
          }
        },
        "overrides": []
      },
      "gridPos": {
        "h": 8,
        "w": 12,
        "x": 12,
        "y": 0
      },
      "id": 2,
      "options": {
        "legend": {
          "calcs": [],
          "displayMode": "list",
          "placement": "bottom",
          "showLegend": true
        },
        "tooltip": {
          "mode": "single",
          "sort": "none"
        }
      },
      "targets": [
        {
          "datasource": {
            "type": "grafana-postgresql-datasource",
            "uid": "e47d9667-cfa2-47f7-841f-2031975ca3d6"
          },
          "editorMode": "code",
          "format": "table",
          "rawQuery": true,
          "rawSql": "select created_on as time\n, 1 as outage\nfrom latency_metric\nwhere latency_ms is null or latency_ms = 0;",
          "refId": "A",
          "sql": {
            "columns": [
              {
                "parameters": [],
                "type": "function"
              }
            ],
            "groupBy": [
              {
                "property": {
                  "type": "string"
                },
                "type": "groupBy"
              }
            ],
            "limit": 50
          }
        }
      ],
      "title": "Outages",
      "type": "timeseries"
    },
    {
      "datasource": {
        "type": "grafana-postgresql-datasource",
        "uid": "e47d9667-cfa2-47f7-841f-2031975ca3d6"
      },
      "fieldConfig": {
        "defaults": {
          "color": {
            "fixedColor": "purple",
            "mode": "fixed"
          },
          "custom": {
            "axisBorderShow": false,
            "axisCenteredZero": false,
            "axisColorMode": "text",
            "axisLabel": "",
            "axisPlacement": "auto",
            "barAlignment": 0,
            "drawStyle": "points",
            "fillOpacity": 0,
            "gradientMode": "none",
            "hideFrom": {
              "legend": false,
              "tooltip": false,
              "viz": false
            },
            "insertNulls": false,
            "lineInterpolation": "linear",
            "lineWidth": 1,
            "pointSize": 3,
            "scaleDistribution": {
              "type": "linear"
            },
            "showPoints": "auto",
            "spanNulls": false,
            "stacking": {
              "group": "A",
              "mode": "none"
            },
            "thresholdsStyle": {
              "mode": "area"
            }
          },
          "mappings": [],
          "thresholds": {
            "mode": "absolute",
            "steps": [
              {
                "color": "green",
                "value": null
              },
              {
                "color": "red",
                "value": 50
              }
            ]
          }
        },
        "overrides": []
      },
      "gridPos": {
        "h": 11,
        "w": 24,
        "x": 0,
        "y": 8
      },
      "id": 1,
      "options": {
        "legend": {
          "calcs": [],
          "displayMode": "list",
          "placement": "bottom",
          "showLegend": true
        },
        "tooltip": {
          "mode": "single",
          "sort": "none"
        }
      },
      "targets": [
        {
          "datasource": {
            "type": "grafana-postgresql-datasource",
            "uid": "e47d9667-cfa2-47f7-841f-2031975ca3d6"
          },
          "editorMode": "code",
          "format": "table",
          "rawQuery": true,
          "rawSql": "select created_on as time\n, case\n     when latency_ms is null then 0\n     else latency_ms\nend as latency_ms\nfrom latency_metric;",
          "refId": "A",
          "sql": {
            "columns": [
              {
                "parameters": [],
                "type": "function"
              }
            ],
            "groupBy": [
              {
                "property": {
                  "type": "string"
                },
                "type": "groupBy"
              }
            ],
            "limit": 50
          }
        }
      ],
      "title": "Latency (ms)",
      "type": "timeseries"
    },
    {
      "datasource": {
        "type": "grafana-postgresql-datasource",
        "uid": "e47d9667-cfa2-47f7-841f-2031975ca3d6"
      },
      "fieldConfig": {
        "defaults": {
          "color": {
            "fixedColor": "purple",
            "mode": "fixed"
          },
          "custom": {
            "axisBorderShow": false,
            "axisCenteredZero": false,
            "axisColorMode": "text",
            "axisLabel": "",
            "axisPlacement": "auto",
            "barAlignment": 0,
            "drawStyle": "line",
            "fillOpacity": 0,
            "gradientMode": "none",
            "hideFrom": {
              "legend": false,
              "tooltip": false,
              "viz": false
            },
            "insertNulls": false,
            "lineInterpolation": "linear",
            "lineWidth": 1,
            "pointSize": 4,
            "scaleDistribution": {
              "type": "linear"
            },
            "showPoints": "auto",
            "spanNulls": false,
            "stacking": {
              "group": "A",
              "mode": "none"
            },
            "thresholdsStyle": {
              "mode": "area"
            }
          },
          "mappings": [],
          "thresholds": {
            "mode": "absolute",
            "steps": [
              {
                "color": "red",
                "value": null
              },
              {
                "color": "green",
                "value": 100
              }
            ]
          }
        },
        "overrides": []
      },
      "gridPos": {
        "h": 11,
        "w": 24,
        "x": 0,
        "y": 19
      },
      "id": 3,
      "options": {
        "legend": {
          "calcs": [],
          "displayMode": "list",
          "placement": "bottom",
          "showLegend": true
        },
        "tooltip": {
          "mode": "single",
          "sort": "none"
        }
      },
      "targets": [
        {
          "datasource": {
            "type": "grafana-postgresql-datasource",
            "uid": "e47d9667-cfa2-47f7-841f-2031975ca3d6"
          },
          "editorMode": "code",
          "format": "table",
          "rawQuery": true,
          "rawSql": "select created_on as time\n, case\n     when download_kbs is null then 0\n     else download_kbs / 1024.0\nend as download_mbps\nfrom bandwidth_metric;",
          "refId": "A",
          "sql": {
            "columns": [
              {
                "parameters": [],
                "type": "function"
              }
            ],
            "groupBy": [
              {
                "property": {
                  "type": "string"
                },
                "type": "groupBy"
              }
            ],
            "limit": 50
          }
        }
      ],
      "title": "Download (mbps)",
      "type": "timeseries"
    },
    {
      "datasource": {
        "type": "grafana-postgresql-datasource",
        "uid": "e47d9667-cfa2-47f7-841f-2031975ca3d6"
      },
      "fieldConfig": {
        "defaults": {
          "color": {
            "fixedColor": "purple",
            "mode": "fixed"
          },
          "custom": {
            "axisBorderShow": false,
            "axisCenteredZero": false,
            "axisColorMode": "text",
            "axisLabel": "",
            "axisPlacement": "auto",
            "barAlignment": 0,
            "drawStyle": "line",
            "fillOpacity": 0,
            "gradientMode": "none",
            "hideFrom": {
              "legend": false,
              "tooltip": false,
              "viz": false
            },
            "insertNulls": false,
            "lineInterpolation": "linear",
            "lineWidth": 1,
            "pointSize": 4,
            "scaleDistribution": {
              "type": "linear"
            },
            "showPoints": "auto",
            "spanNulls": false,
            "stacking": {
              "group": "A",
              "mode": "none"
            },
            "thresholdsStyle": {
              "mode": "area"
            }
          },
          "mappings": [],
          "thresholds": {
            "mode": "absolute",
            "steps": [
              {
                "color": "red",
                "value": null
              },
              {
                "color": "green",
                "value": 5
              }
            ]
          }
        },
        "overrides": []
      },
      "gridPos": {
        "h": 11,
        "w": 24,
        "x": 0,
        "y": 30
      },
      "id": 4,
      "options": {
        "legend": {
          "calcs": [],
          "displayMode": "list",
          "placement": "bottom",
          "showLegend": true
        },
        "tooltip": {
          "mode": "single",
          "sort": "none"
        }
      },
      "targets": [
        {
          "datasource": {
            "type": "grafana-postgresql-datasource",
            "uid": "e47d9667-cfa2-47f7-841f-2031975ca3d6"
          },
          "editorMode": "code",
          "format": "table",
          "rawQuery": true,
          "rawSql": "select created_on as time\n, case\n     when upload_kbs is null then 0\n     else upload_kbs / 1024.0\nend as upload_mbps\nfrom bandwidth_metric;",
          "refId": "A",
          "sql": {
            "columns": [
              {
                "parameters": [],
                "type": "function"
              }
            ],
            "groupBy": [
              {
                "property": {
                  "type": "string"
                },
                "type": "groupBy"
              }
            ],
            "limit": 50
          }
        }
      ],
      "title": "Upload (mbps)",
      "type": "timeseries"
    }
  ],
  "refresh": false,
  "schemaVersion": 39,
  "tags": [],
  "templating": {
    "list": []
  },
  "time": {
    "from": "now-24h",
    "to": "now"
  },
  "timepicker": {},
  "timezone": "",
  "title": "Network Monitoring",
  "uid": "cc862c85-5c11-482f-8854-b4e2a3e01f57",
  "version": 7,
  "weekStart": ""
}
